elkme/__init__.py
elkme/config.py
elkme/elks.py
elkme/helpers.py
elkme/main.py
elkme-0.6.0.dist-info/DESCRIPTION.rst
elkme-0.6.0.dist-info/METADATA
elkme-0.6.0.dist-info/RECORD
elkme-0.6.0.dist-info/WHEEL
elkme-0.6.0.dist-info/entry_points.txt
elkme-0.6.0.dist-info/metadata.json
elkme-0.6.0.dist-info/top_level.txt
