Metadata-Version: 2.0
Name: elkme
Version: 0.6.0
Summary: Command-line tool and SDK for sending SMS
Home-page: https://github.com/46elks/elkme
Author: Emil Tullstedt
Author-email: emil@46elks.com
License: MIT
Keywords: sms 46elks cli monitoring
Platform: UNKNOWN
Classifier: Development Status :: 4 - Beta
Classifier: Environment :: Console
Classifier: Intended Audience :: System Administrators
Classifier: Intended Audience :: Developers
Classifier: License :: OSI Approved :: MIT License
Classifier: Programming Language :: Python :: 2
Classifier: Programming Language :: Python :: 2.6
Classifier: Programming Language :: Python :: 2.7
Classifier: Programming Language :: Python :: 3
Classifier: Programming Language :: Python :: 3.4
Classifier: Programming Language :: Python :: 3.5
Classifier: Topic :: Software Development :: Libraries
Classifier: Topic :: System :: Monitoring
Requires-Dist: requests (>=2.10.0)
